atroposlib/FAQ.md
atroposlib/__init__.py
atroposlib/type_definitions.py
atroposlib/api/README.md
atroposlib/api/__init__.py
atroposlib/api/env_interaction.md
atroposlib/api/server.py
atroposlib/api/trainer_interaction.md
atroposlib/api/utils.py
atroposlib/cli/dpo.py
atroposlib/cli/inference_node_wandb_watcher.py
atroposlib/cli/run_api.py
atroposlib/cli/sft.py
atroposlib/cli/view_run.py
atroposlib/cli/view_run_multimodal.py
atroposlib/envs/README.md
atroposlib/envs/__init__.py
atroposlib/envs/base.py
atroposlib/envs/constants.py
atroposlib/envs/reward_fns/__init__.py
atroposlib/envs/reward_fns/accuracy_reward.py
atroposlib/envs/reward_fns/cascading_r1_math_reward.py
atroposlib/envs/reward_fns/chandas_meter_reward.py
atroposlib/envs/reward_fns/combined_reward.py
atroposlib/envs/reward_fns/cosine_scaled_reward.py
atroposlib/envs/reward_fns/crossword_format_reward.py
atroposlib/envs/reward_fns/format_reward.py
atroposlib/envs/reward_fns/r1_reward.py
atroposlib/envs/reward_fns/reasoning_steps_reward.py
atroposlib/envs/reward_fns/registry.py
atroposlib/envs/reward_fns/repetition_penalty_reward.py
atroposlib/envs/reward_fns/reward_function.py
atroposlib/envs/server_handling/openai_server.py
atroposlib/envs/server_handling/server_baseline.py
atroposlib/envs/server_handling/server_harness.py
atroposlib/envs/server_handling/server_manager.py
atroposlib/envs/server_handling/trl_vllm_server.py
atroposlib/frontend/jsonl2html.py
atroposlib/frontend/template.html
atroposlib/tests/README.md
atroposlib/tests/api_test_utils.py
atroposlib/tests/conftest.py
atroposlib/tests/test_advantages.py
atroposlib/tests/test_api_legacy.py
atroposlib/tests/test_api_messages_handling.py
atroposlib/tests/test_api_messages_handling_README.md
atroposlib/tests/test_openai_api_workarounds.py
atroposlib/tests/test_utils/__init__.py
atroposlib/tests/test_utils/test_heterogeneous_batching.py
atroposlib/tests/test_utils/test_heterogeneous_packing.py
atroposlib/tests/test_utils/test_min_batch_allocation.py
atroposlib-0.3.0.dist-info/METADATA
atroposlib-0.3.0.dist-info/WHEEL
atroposlib-0.3.0.dist-info/entry_points.txt
atroposlib-0.3.0.dist-info/licenses/LICENSE
atroposlib-0.3.0.dist-info/RECORD
