Metadata-Version: 2.4
Name: atroposlib
Version: 0.3.0
Summary: Atropos: An Environment and Rollout handler for LLM RL
License-File: LICENSE
Requires-Python: >=3.10
Requires-Dist: aiofiles
Requires-Dist: aiohttp
Requires-Dist: datasets
Requires-Dist: fastapi
Requires-Dist: gymnasium
Requires-Dist: hf-transfer
Requires-Dist: jinja2
Requires-Dist: jsonlines
Requires-Dist: markdown
Requires-Dist: math-verify==0.7.0
Requires-Dist: nltk
Requires-Dist: numpy
Requires-Dist: openai
Requires-Dist: polars
Requires-Dist: pydantic-cli
Requires-Dist: rich
Requires-Dist: tenacity
Requires-Dist: tqdm
Requires-Dist: transformers
Requires-Dist: uvicorn[standard]
Requires-Dist: wandb
Provides-Extra: all
Requires-Dist: black; extra == 'all'
Requires-Dist: flake8; extra == 'all'
Requires-Dist: gradio; extra == 'all'
Requires-Dist: isort; extra == 'all'
Requires-Dist: langdetect; extra == 'all'
Requires-Dist: mypy; extra == 'all'
Requires-Dist: pre-commit; extra == 'all'
Requires-Dist: pytest; extra == 'all'
Requires-Dist: pytest-asyncio; extra == 'all'
Requires-Dist: rich; extra == 'all'
Requires-Dist: torch; extra == 'all'
Provides-Extra: dev
Requires-Dist: black; extra == 'dev'
Requires-Dist: flake8; extra == 'dev'
Requires-Dist: isort; extra == 'dev'
Requires-Dist: mypy; extra == 'dev'
Requires-Dist: pre-commit; extra == 'dev'
Requires-Dist: pytest; extra == 'dev'
Requires-Dist: pytest-asyncio; extra == 'dev'
Requires-Dist: rich; extra == 'dev'
Provides-Extra: examples
Requires-Dist: gradio; extra == 'examples'
Requires-Dist: langdetect; extra == 'examples'
Requires-Dist: torch; extra == 'examples'
Provides-Extra: rewardfns
Requires-Dist: torch; extra == 'rewardfns'
